ds_connectors/__init__.py
ds_connectors/handlers/__init__.py
ds_connectors/handlers/cortex_helpers.py
ds_connectors/handlers/hive_handlers.py
ds_connectors/handlers/mc_handlers.py
ds_connectors/handlers/mongodb_handlers.py
ds_connectors/handlers/mysql_handlers.py
ds_connectors/handlers/oracle_handlers.py
ds_connectors/handlers/postgres_handlers.py
ds_connectors/handlers/redis_handlers.py
ds_connectors/parsers/__init__.py
ds_connectors/parsers/dsv.py
tests/aws/__init__.py
tests/aws/s3_handler_test.py
tests/handlers/__init__.py
tests/managed_content/__init__.py
tests/managed_content/mc_handler_test.py
tests/mongodb/__init__.py
tests/mongodb/mongodb_handler_test.py
tests/mysql/__init__.py
tests/mysql/mysql_handler_test.py
tests/po1/__init__.py
discovery_connectors-1.4.4.dist-info/LICENSE.txt
discovery_connectors-1.4.4.dist-info/METADATA
discovery_connectors-1.4.4.dist-info/WHEEL
discovery_connectors-1.4.4.dist-info/top_level.txt
discovery_connectors-1.4.4.dist-info/RECORD
